LICENSE.txt
README.md
setup.py
dualbounds/__init__.py
dualbounds/bootstrap.py
dualbounds/delta.py
dualbounds/dist_reg.py
dualbounds/gen_data.py
dualbounds/generic.py
dualbounds/interpolation.py
dualbounds/iv.py
dualbounds/lee.py
dualbounds/utilities.py
dualbounds/varcate.py
dualbounds/varite.py
dualbounds.egg-info/PKG-INFO
dualbounds.egg-info/SOURCES.txt
dualbounds.egg-info/dependency_links.txt
dualbounds.egg-info/requires.txt
dualbounds.egg-info/top_level.txt
test/__init__.py
test/context.py
test/test_bootstrap.py
test/test_delta.py
test/test_dist_reg.py
test/test_generic.py
test/test_interp.py
test/test_iv.py
test/test_lee.py
test/test_utils.py
test/test_varbounds.py