Metadata-Version: 2.1
Name: dualbounds
Version: 2.0.0
Summary: Dual bounds for model-agnostic inference
Home-page: https://github.com/amspector100/dualbounds/
Author: Asher Spector
Author-email: amspector100@gmail.com
Classifier: Programming Language :: Python :: 3
Classifier: License :: OSI Approved :: MIT License
Classifier: Operating System :: OS Independent
Requires-Python: >=3.9
License-File: LICENSE.txt
